flask_docusign/__init__.py
flask_docusign/api.py
flask_docusign/calls.py
flask_docusign/client.py
flask_docusign/dto.py
flask_docusign/patch.py
flask_docusign-0.1.2.dist-info/METADATA
flask_docusign-0.1.2.dist-info/WHEEL
flask_docusign-0.1.2.dist-info/top_level.txt
flask_docusign-0.1.2.dist-info/RECORD
