Metadata-Version: 2.1
Name: flask-docusign
Version: 0.1.2
Summary: Simple DocuSign client for Flask
Home-page: https://github.com/adyachok/flask-docusign
Author: Andras Gyacsok
Author-email: atti.dyachok@gmail.com
License: MIT
Platform: UNKNOWN
Requires-Dist: certifi (==2021.5.30)
Requires-Dist: cffi (==1.14.6)
Requires-Dist: chardet (==4.0.0)
Requires-Dist: click (==8.0.1)
Requires-Dist: cryptography (==3.4.7)
Requires-Dist: docusign-esign (==3.10.0)
Requires-Dist: fastapi-camelcase (==1.0.2)
Requires-Dist: Flask (==2.0.1)
Requires-Dist: idna (==2.10)
Requires-Dist: itsdangerous (==2.0.1)
Requires-Dist: Jinja2 (==3.0.1)
Requires-Dist: MarkupSafe (==2.0.1)
Requires-Dist: nose (==1.3.7)
Requires-Dist: pycparser (==2.20)
Requires-Dist: pydantic (==1.8.2)
Requires-Dist: pydantic[email]
Requires-Dist: pyhumps (==3.0.2)
Requires-Dist: PyJWT (==1.7.1)
Requires-Dist: python-dateutil (==2.8.1)
Requires-Dist: pytz
Requires-Dist: requests (==2.25.1)
Requires-Dist: six (==1.16.0)
Requires-Dist: typing-extensions (==3.10.0.0)
Requires-Dist: urllib3 (==1.26.6)
Requires-Dist: Werkzeug (==2.0.1)
